simcom/__init__.py
simcom-0.0.2.dist-info/LICENSE
simcom-0.0.2.dist-info/METADATA
simcom-0.0.2.dist-info/WHEEL
simcom-0.0.2.dist-info/top_level.txt
simcom-0.0.2.dist-info/RECORD
